tree_parsing/__init__.py
tree_parsing/tree.py
tree_parsing-0.1.1.dist-info/LICENSE
tree_parsing-0.1.1.dist-info/METADATA
tree_parsing-0.1.1.dist-info/WHEEL
tree_parsing-0.1.1.dist-info/RECORD
