Metadata-Version: 2.1
Name: tree-parsing
Version: 0.1.1
Summary: library to work with tree and lists
Home-page: https://github.com/scjorge/tree-parsing
License: MIT
Keywords: node,tree,json,json-schema,hints,parsin,parsing,workflow
Author: Jorge Silva
Author-email: jorgesilva.ti@hotmail.com
Maintainer: Jorge Silva
Maintainer-email: jorgesilva.ti@hotmail.com
Requires-Python: >=3.8,<4.0
Classifier: Intended Audience :: Developers
Classifier: Intended Audience :: Information Technology
Classifier: License :: OSI Approved :: MIT License
Classifier: Natural Language :: English
Classifier: Programming Language :: Python :: 3
Classifier: Programming Language :: Python :: 3.8
Classifier: Programming Language :: Python :: 3.9
Classifier: Programming Language :: Python :: 3.10
Classifier: Programming Language :: Python :: 3.11
Project-URL: Documentation, https://tree-parsing.readthedocs.io/en/latest/
Project-URL: Repository, https://github.com/scjorge/tree-parsing
